gpf/__init__.py
gpf/cursors.py
gpf/loggers.py
gpf/lookups.py
gpf/paths.py
gpf/common/__init__.py
gpf/common/const.py
gpf/common/guids.py
gpf/common/textutils.py
gpf/common/validate.py
gpf/tools/__init__.py
gpf/tools/fieldutils.py
gpf/tools/geometry.py
gpf/tools/maputils.py
gpf/tools/metadata.py
gpf/tools/queries.py
gpf3-0.3.2.dist-info/LICENSE
gpf3-0.3.2.dist-info/METADATA
gpf3-0.3.2.dist-info/WHEEL
gpf3-0.3.2.dist-info/top_level.txt
gpf3-0.3.2.dist-info/RECORD
