Metadata-Version: 2.1
Name: gpf3
Version: 0.3.2
Summary: Geocom Python Framework for ArcPy (Esri ArcGIS Pro).
Home-page: https://github.com/geocom-gis/gpf3
Author: Geocom Informatik AG / VertiGIS, Burgdorf, Switzerland
Author-email: github@geocom.ch
License: Apache License 2.0
Project-URL: Source, https://github.com/geocom-gis/gpf3
Project-URL: Documentation, https://gpf3.readthedocs.io/
Keywords: Geocom,GIS,GEONIS,tools,scripting,framework,spatial,geospatial,geoprocessing,Esri,ArcGIS,ArcPy,VertiGIS
Platform: UNKNOWN
Classifier: Development Status :: 4 - Beta
Classifier: Intended Audience :: Developers
Classifier: Environment :: Other Environment
Classifier: Operating System :: Microsoft :: Windows
Classifier: Topic :: Scientific/Engineering :: GIS
Classifier: License :: OSI Approved :: Apache Software License
Classifier: Programming Language :: Python :: 3.6
Requires-Python: >=3.6
Provides-Extra: test
Requires-Dist: pytest ; extra == 'test'
Requires-Dist: pytest-cov ; extra == 'test'
Requires-Dist: mock ; extra == 'test'
Requires-Dist: pytest-mock ; extra == 'test'
